src/__init__.py
src/builds.py
src/printing.py
src/remote.py
src/uconf.py
src/uinstall.py
sbutils_remote-0.0.2.dist-info/METADATA
sbutils_remote-0.0.2.dist-info/WHEEL
sbutils_remote-0.0.2.dist-info/entry_points.txt
sbutils_remote-0.0.2.dist-info/top_level.txt
sbutils_remote-0.0.2.dist-info/RECORD
